zero_config/__init__.py
zero_config/config.py
zero_config-0.1.6.dist-info/licenses/LICENSE
zero_config-0.1.6.dist-info/METADATA
zero_config-0.1.6.dist-info/WHEEL
zero_config-0.1.6.dist-info/top_level.txt
zero_config-0.1.6.dist-info/RECORD
