Metadata-Version: 2.4
Name: zero-config
Version: 0.1.6
Summary: A zero-configuration library with smart environment variable support and type-aware defaults
Home-page: https://github.com/zero-config/zero-config
Author: Michael Chen
Author-email: Michael Chen <xychen@msn.com>
License: MIT
Project-URL: Homepage, https://github.com/zero-config/zero-config
Project-URL: Bug Tracker, https://github.com/zero-config/zero-config/issues
Project-URL: Documentation, https://zero-config.readthedocs.io/
Classifier: Programming Language :: Python :: 3
Classifier: License :: OSI Approved :: MIT License
Classifier: Operating System :: OS Independent
Classifier: Development Status :: 4 - Beta
Classifier: Intended Audience :: Developers
Classifier: Topic :: Software Development :: Libraries :: Python Modules
Classifier: Topic :: System :: Systems Administration
Requires-Python: >=3.7
License-File: LICENSE
Requires-Dist: python-dotenv>=0.19.0
Provides-Extra: dev
Requires-Dist: pytest>=6.0; extra == "dev"
Requires-Dist: pytest-cov>=2.0; extra == "dev"
Requires-Dist: black>=21.0; extra == "dev"
Requires-Dist: flake8>=3.8; extra == "dev"
Requires-Dist: mypy>=0.800; extra == "dev"
Dynamic: license-file
